llama_index/llms/groq/__init__.py
llama_index/llms/groq/base.py
llama_index_llms_groq-0.4.0.dist-info/METADATA
llama_index_llms_groq-0.4.0.dist-info/WHEEL
llama_index_llms_groq-0.4.0.dist-info/licenses/LICENSE
llama_index_llms_groq-0.4.0.dist-info/RECORD
